README.md
config.ini.example
dfn_pki_client/PN_Robert_Graetz_-_Charite_Teilnehmerservice_Berlin_2021-01-04.p12
dfn_pki_client/__init__.py
dfn_pki_client/client_authentication.py
dfn_pki_client/domain_service.py
dfn_pki_client/function_emails.csv
dfn_pki_client/main.py
dfn_pki_client/objects.py
dfn_pki_client/openssl.py
dfn_pki_client/public_service.py
dfn_pki_client/registration_service.py
dfn_pki_client/test.py
dfn_pki_client/test2.py
dfn_pki_client/test3.py
dfn_pki_client/test4.py
dfn_pki_client/test5.py
dfn_pki_client/utils.py
dfn_pki_client-0.1.4.3.dist-info/entry_points.txt
dfn_pki_client-0.1.4.3.dist-info/WHEEL
dfn_pki_client-0.1.4.3.dist-info/METADATA
dfn_pki_client-0.1.4.3.dist-info/RECORD
