Metadata-Version: 2.1
Name: dfn-pki-client
Version: 0.1.4.3
Summary: Python module for the DFN-PKI soap API
Home-page: https://github.com/ikreb7/DFN-PKI-Client
License: GPL-3.0-or-later
Author: Robert Grätz
Requires-Python: >=3.6,<4.0
Classifier: License :: OSI Approved :: GNU General Public License v3 or later (GPLv3+)
Classifier: Programming Language :: Python :: 3
Classifier: Programming Language :: Python :: 3.6
Classifier: Programming Language :: Python :: 3.7
Classifier: Programming Language :: Python :: 3.8
Classifier: Programming Language :: Python :: 3.9
Requires-Dist: click (>=7.1.2,<8.0.0)
Requires-Dist: cryptography (>=3.4.5,<4.0.0)
Requires-Dist: pyOpenSSL (>=20.0.1,<21.0.0)
Requires-Dist: suds-community (>=0.8.4,<0.9.0)
Requires-Dist: urllib3 (>=1.26.3,<2.0.0)
Project-URL: Documentation, https://github.com/ikreb7/DFN-PKI-Client
Project-URL: Repository, https://github.com/ikreb7/DFN-PKI-Client
